hemlock_berlin/__init__.py
hemlock_berlin-0.0.3.dist-info/LICENSE
hemlock_berlin-0.0.3.dist-info/METADATA
hemlock_berlin-0.0.3.dist-info/WHEEL
hemlock_berlin-0.0.3.dist-info/top_level.txt
hemlock_berlin-0.0.3.dist-info/RECORD
